{
  "project_info": {
    "project_number": "519994687640",
    "project_id": "rmrs-customer",
    "storage_bucket": "rmrs-customer.appspot.com"
  },
  "client": [
    {
      "client_info": {
        "mobilesdk_app_id": "1:519994687640:android:194fac957909e9801050ed",
        "android_client_info": {
          "package_name": "com.comcept.rmrscustomer"
        }
      },
      "oauth_client": [
        {
          "client_id": "519994687640-1nmpl9sejpls64ifi810faf8sq89vdj2.apps.googleusercontent.com",
          "client_type": 1,
          "android_info": {
            "package_name": "com.comcept.rmrscustomer",
            "certificate_hash": "df1959a6db060a55515c66cc51b3f43d98b78ddb"
          }
        },
        {
          "client_id": "519994687640-5m74ajg3r948ls5s2roeh9podfvadao5.apps.googleusercontent.com",
          "client_type": 1,
          "android_info": {
            "package_name": "com.comcept.rmrscustomer",
            "certificate_hash": "5d85c81abcbca1d4647438a4bf816b41c3b20fcc"
          }
        },
        {
          "client_id": "519994687640-7h00olttvp8jbjn1nch7qnreigqt8j35.apps.googleusercontent.com",
          "client_type": 1,
          "android_info": {
            "package_name": "com.comcept.rmrscustomer",
            "certificate_hash": "6282ff9767bf12e903ed81a9329d557b281d0891"
          }
        },
        {
          "client_id": "519994687640-vfm4vljs8pemache260gh3t8d6l6383s.apps.googleusercontent.com",
          "client_type": 1,
          "android_info": {
            "package_name": "com.comcept.rmrscustomer",
            "certificate_hash": "d6ed29bdc2812e3f1f922050ae907903bb73ab57"
          }
        },
        {
          "client_id": "519994687640-1gobrtbkgac66jmns09kp2h7jei5lt68.apps.googleusercontent.com",
          "client_type": 3
        }
      ],
      "api_key": [
        {
          "current_key": "AIzaSyD6DWfBziYi7fIxE_YZe0fD3M_1aWiRJDI"
        }
      ],
      "services": {
        "appinvite_service": {
          "other_platform_oauth_client": [
            {
              "client_id": "519994687640-1gobrtbkgac66jmns09kp2h7jei5lt68.apps.googleusercontent.com",
              "client_type": 3
            }
          ]
        }
      }
    }
  ],
  "configuration_version": "1"
}